azure/cli/core/__init__.py
azure/cli/core/_completers.py
azure/cli/core/_config.py
azure/cli/core/_debug.py
azure/cli/core/_environment.py
azure/cli/core/_help.py
azure/cli/core/_help_loaders.py
azure/cli/core/_identity.py
azure/cli/core/_msal.py
azure/cli/core/_msal_patch.py
azure/cli/core/_output.py
azure/cli/core/_profile.py
azure/cli/core/_session.py
azure/cli/core/api.py
azure/cli/core/azclierror.py
azure/cli/core/azlogging.py
azure/cli/core/cloud.py
azure/cli/core/command_recommender.py
azure/cli/core/credential.py
azure/cli/core/decorators.py
azure/cli/core/file_util.py
azure/cli/core/keys.py
azure/cli/core/local_context.py
azure/cli/core/mock.py
azure/cli/core/msal_authentication.py
azure/cli/core/parser.py
azure/cli/core/style.py
azure/cli/core/telemetry.py
azure/cli/core/util.py
azure/cli/core/auth_landing_pages/fail.html
azure/cli/core/auth_landing_pages/ok.html
azure/cli/core/commands/__init__.py
azure/cli/core/commands/arm.py
azure/cli/core/commands/client_factory.py
azure/cli/core/commands/constants.py
azure/cli/core/commands/events.py
azure/cli/core/commands/parameters.py
azure/cli/core/commands/progress.py
azure/cli/core/commands/query_examples.py
azure/cli/core/commands/template_create.py
azure/cli/core/commands/transform.py
azure/cli/core/commands/validators.py
azure/cli/core/extension/__init__.py
azure/cli/core/extension/_homebrew_patch.py
azure/cli/core/extension/_index.py
azure/cli/core/extension/_resolve.py
azure/cli/core/extension/operations.py
azure/cli/core/profiles/__init__.py
azure/cli/core/profiles/_shared.py
azure/cli/core/vendored_sdks/__init__.py
azure/cli/core/vendored_sdks/subscriptions/__init__.py
azure/cli/core/vendored_sdks/subscriptions/_configuration.py
azure/cli/core/vendored_sdks/subscriptions/_operations_mixin.py
azure/cli/core/vendored_sdks/subscriptions/_subscription_client.py
azure/cli/core/vendored_sdks/subscriptions/_version.py
azure/cli/core/vendored_sdks/subscriptions/models.py
msgraph_cli_core-2.25.0.6.dist-info/METADATA
msgraph_cli_core-2.25.0.6.dist-info/WHEEL
msgraph_cli_core-2.25.0.6.dist-info/top_level.txt
msgraph_cli_core-2.25.0.6.dist-info/RECORD
