Metadata-Version: 2.1
Name: msgraph-cli-core
Version: 2.25.0.6
Summary: Microsoft Azure Command-Line Tools Core Module
Home-page: https://github.com/Azure/azure-cli
Author: Microsoft Corporation
Author-email: azpycli@microsoft.com
License: MIT
Platform: UNKNOWN
Classifier: Development Status :: 5 - Production/Stable
Classifier: Intended Audience :: Developers
Classifier: Intended Audience :: System Administrators
Classifier: Programming Language :: Python
Classifier: Programming Language :: Python :: 3
Classifier: Programming Language :: Python :: 3.6
Classifier: Programming Language :: Python :: 3.7
Classifier: Programming Language :: Python :: 3.8
Classifier: License :: OSI Approved :: MIT License
Requires-Python: >=3.6.0
Requires-Dist: adal (~=1.2.7)
Requires-Dist: argcomplete (~=1.8)
Requires-Dist: azure-cli-telemetry (==1.0.6.*)
Requires-Dist: azure-common (~=1.1)
Requires-Dist: azure-core (==1.14.0b1)
Requires-Dist: azure-identity (==1.6.0b3)
Requires-Dist: azure-mgmt-core (==1.3.0b1)
Requires-Dist: colorama (~=0.4.1)
Requires-Dist: cryptography (>=3.4)
Requires-Dist: humanfriendly (<10.0,>=4.7)
Requires-Dist: jmespath
Requires-Dist: knack (~=0.8.0)
Requires-Dist: msrest (>=0.5.0)
Requires-Dist: msrestazure (>=0.6.3)
Requires-Dist: paramiko (<3.0.0,>=2.0.8)
Requires-Dist: pkginfo (>=1.5.0.1)
Requires-Dist: PyJWT (==1.7.1)
Requires-Dist: pyopenssl (>=17.1.0)
Requires-Dist: requests (~=2.22)
Requires-Dist: six (~=1.12)
Requires-Dist: psutil (~=5.8)
Provides-Extra: test
Requires-Dist: mock ; extra == 'test'
